CHANGELOG.md
README.md
mitol/__init__.py
mitol/common/__init__.py
mitol/common/admin.py
mitol/common/apps.py
mitol/common/constants.py
mitol/common/decorators.py
mitol/common/envs.py
mitol/common/models.py
mitol/common/py.typed
mitol/common/pytest_utils.py
mitol/common/factories/__init__.py
mitol/common/factories/defaults.py
mitol/common/management/__init__.py
mitol/common/management/commands/__init__.py
mitol/common/management/commands/generate_app_json.py
mitol/common/settings/__init__.py
mitol/common/settings/base.py
mitol/common/settings/celery.py
mitol/common/settings/webpack.py
mitol/common/templatetags/render_bundle.py
mitol/common/utils/__init__.py
mitol/common/utils/base.py
mitol/common/utils/celery.py
mitol/common/utils/collections.py
mitol/common/utils/config.py
mitol/common/utils/currency.py
mitol/common/utils/datetime.py
mitol/common/utils/helpers.py
mitol/common/utils/http_requests.py
mitol/common/utils/serializers.py
mitol/common/utils/urls.py
mitol/common/utils/user.py
mitol/common/utils/webpack.py
mitol_django_common-2025.12.23.2.dist-info/METADATA
mitol_django_common-2025.12.23.2.dist-info/WHEEL
mitol_django_common-2025.12.23.2.dist-info/RECORD
