Metadata-Version: 2.4
Name: mitol-django-common
Version: 2025.12.23.2
Summary: MIT Open Learning django app extensions for common utilities
License-Expression: BSD-3-Clause
Requires-Python: >=3.10
Requires-Dist: django-redis~=6.0
Requires-Dist: django-stubs>=1.13.1
Requires-Dist: django-webpack-loader>=0.7.0
Requires-Dist: django>=3.0
Requires-Dist: factory-boy~=3.2
Requires-Dist: pytest<10,>=9
Requires-Dist: pytz>=2020.4
Requires-Dist: requests>=2.20.0
Requires-Dist: typing-extensions
Provides-Extra: celery
Requires-Dist: celery>=5.5.0; extra == 'celery'
